valohai_meta_pkg/__about__.py
valohai_meta_pkg/__init__.py
valohai-0.0.1.dist-info/METADATA
valohai-0.0.1.dist-info/WHEEL
valohai-0.0.1.dist-info/licenses/LICENSE.txt
valohai-0.0.1.dist-info/RECORD
