Metadata-Version: 2.1
Name: valohai
Version: 0.0.1
Summary: Meta-package to require `valohai-cli` and `valohai-utils`.
Author-email: Aarni Koskela <akx@iki.fi>
License-Expression: MIT
License-File: LICENSE.txt
Requires-Python: >=3
Requires-Dist: valohai-cli
Requires-Dist: valohai-utils
